CHANGELOG.rst
LICENSE
MANIFEST.in
README.rst
coverage.ini
pytest.ini
setup.py
tox.ini
pytest_curl_report/__init__.py
pytest_curl_report/curl.py
pytest_curl_report/plugin.py
pytest_curl_report/utils.py
pytest_curl_report.egg-info/PKG-INFO
pytest_curl_report.egg-info/SOURCES.txt
pytest_curl_report.egg-info/dependency_links.txt
pytest_curl_report.egg-info/entry_points.txt
pytest_curl_report.egg-info/requires.txt
pytest_curl_report.egg-info/top_level.txt
tests/data.py
tests/test_misc.py
tests/test_requests.py
tests/test_urllib.py
tests/utils.py
tests/fixtures/attach.txt
tests/fixtures/添付.txt